dancesport_parser/__init__.py
dancesport_parser/util.py
dancesport_parser/o2cm/__init__.py
dancesport_parser/o2cm/model.py
dancesport_parser/o2cm/parser.py
dancesport_parser-0.0.5.dist-info/METADATA
dancesport_parser-0.0.5.dist-info/WHEEL
dancesport_parser-0.0.5.dist-info/licenses/LICENSE
dancesport_parser-0.0.5.dist-info/RECORD
